{
  "total_nodes": 12,
  "nodes": [
    { "reward": 12.5, "staked": 1500 },
    { "reward": 10.2, "staked": 1200 },
    { "reward": 8.7,  "staked": 900 },
    { "reward": 11.1, "staked": 1300 },
    { "reward": 9.8,  "staked": 1100 },
    { "reward": 13.0, "staked": 1600 },
    { "reward": 7.5,  "staked": 800 },
    { "reward": 10.9, "staked": 1250 },
    { "reward": 8.3,  "staked": 950 },
    { "reward": 12.2, "staked": 1450 },
    { "reward": 9.1,  "staked": 1050 },
    { "reward": 11.5, "staked": 1350 }
  ]
}